pgraph/PGraph.py
pgraph/__init__.py
tests/__init__.py
tests/test_graph.py
pgraph_python-0.6.2.dist-info/LICENSE
pgraph_python-0.6.2.dist-info/METADATA
pgraph_python-0.6.2.dist-info/WHEEL
pgraph_python-0.6.2.dist-info/top_level.txt
pgraph_python-0.6.2.dist-info/RECORD
