Metadata-Version: 2.1
Name: pgraph-python
Version: 0.6.2
Summary: Mathematical graphs for Python.
Home-page: https://github.com/petercorke/pgraph-python
Author: Peter Corke
Author-email: rvc@petercorke.com
License: MIT
Project-URL: Source, https://github.com/petercorke/bdsim
Project-URL: Tracker, https://github.com/petercorke/bdsim/issues
Keywords: python graph directed-graph undirected-graph a*-search adjacency-matrix Laplacian-matrix plotting optimal-path
Classifier: Development Status :: 4 - Beta
Classifier: Intended Audience :: Developers
Classifier: License :: OSI Approved :: MIT License
Classifier: Programming Language :: Python :: 3 :: Only
Requires-Python: >=3.6
Provides-Extra: docs
Provides-Extra: dev
License-File: LICENSE
